benchmcmc/__init__.py
benchmcmc/benchmark.py
benchmcmc/mkbench.py
benchmcmc-0.0.7.dist-info/LICENSE
benchmcmc-0.0.7.dist-info/METADATA
benchmcmc-0.0.7.dist-info/WHEEL
benchmcmc-0.0.7.dist-info/entry_points.txt
benchmcmc-0.0.7.dist-info/top_level.txt
benchmcmc-0.0.7.dist-info/RECORD
