Metadata-Version: 2.1
Name: benchmcmc
Version: 0.0.7
Summary: Use MCMC to do benchmark analysis
Home-page: https://github.com/pgdr/benchmcmc
Author: PG Drange
Author-email: pgdr@equinor.com
Maintainer: PG Drange <pgdr@equinor.com>
License: MIT
Project-URL: Bug Tracker, https://github.com/pgdr/benchmcmc/issues
Project-URL: Documentation, https://github.com/pgdr/benchmcmc/blob/master/README.md
Project-URL: Source Code, https://github.com/pgdr/benchmcmc
Keywords: mcmc,bayesian methods,statistics,benchmark analysis,disaster modeling,unix,command line tool
Platform: UNKNOWN
Requires-Dist: matplotlib
Requires-Dist: pymc3
